{
  "/404": "pages/404.js",
  "/_app": "pages/_app.js",
  "/": "pages/index.js",
  "/_error": "pages/_error.js",
  "/_document": "pages/_document.js",
  "/en/500": "pages/en/500.html",
  "/en/components/Footer": "pages/en/components/Footer.html",
  "/en/components/Modal/Common": "pages/en/components/Modal/Common.html",
  "/en/components/Header/decoration": "pages/en/components/Header/decoration.html",
  "/en/components/Modal/Download": "pages/en/components/Modal/Download.html",
  "/en/components/Modal/Palette": "pages/en/components/Modal/Palette.html",
  "/en/components/Modal/Embed": "pages/en/components/Modal/Embed.html",
  "/en/components/AvatarEditor/SelectionWrapper": "pages/en/components/AvatarEditor/SelectionWrapper.html",
  "/en/components/AvatarEditor": "pages/en/components/AvatarEditor.html",
  "/en/components/Code": "pages/en/components/Code.html",
  "/en/components/Account": "pages/en/components/Account.html",
  "/en/components/Address": "pages/en/components/Address.html",
  "/en/components/Header": "pages/en/components/Header.html"
}